bq/dirupload/__init__.py
bq/dirupload/delayqueue.py
bq/dirupload/fetchdir.py
bq/dirupload/metaplugin.py
bq/dirupload/metatable.py
bq/dirupload/pool.py
bq/dirupload/uploaddirp.py
bq/dirupload/version.py
bq/dirupload/watchdirs.py
bq_tools_dirupload-0.8.15.dist-info/METADATA
bq_tools_dirupload-0.8.15.dist-info/WHEEL
bq_tools_dirupload-0.8.15.dist-info/entry_points.txt
bq_tools_dirupload-0.8.15.dist-info/top_level.txt
bq_tools_dirupload-0.8.15.dist-info/RECORD
