Metadata-Version: 2.1
Name: bq-tools-dirupload
Version: 0.8.15
Summary: Upload/Download files to bisque/ViQi in parallel
Author: ViQi Inc
Author-email: info@viqi.org
Project-URL: homepage, https://www.viqi.org
Classifier: Programming Language :: Python :: 3
Classifier: Programming Language :: Python :: 3.8
Classifier: Programming Language :: Python :: 3.10
Requires-Python: >=3.8
Requires-Dist: bisque-api<0.6,>=0.5.10.14
Requires-Dist: viqi-api>=0.6.4.8
Requires-Dist: bisque-metadoc
Requires-Dist: configparser
Requires-Dist: lxml
Requires-Dist: regex>=2020.11.13
Requires-Dist: watchdog
Provides-Extra: exif
Requires-Dist: exif; extra == "exif"
